executor/__init__.py
executor/chroot.py
executor/cli.py
executor/concurrent.py
executor/contexts.py
executor/process.py
executor/schroot.py
executor/tcp.py
executor/tests.py
executor/ssh/__init__.py
executor/ssh/client.py
executor/ssh/server.py
executor-23.1.dist-info/LICENSE.txt
executor-23.1.dist-info/METADATA
executor-23.1.dist-info/WHEEL
executor-23.1.dist-info/entry_points.txt
executor-23.1.dist-info/top_level.txt
executor-23.1.dist-info/RECORD
